fifo_mem.v
module fifo_mem #(parameter DATA_WIDTH = 8, parameter ADDR_WIDTH = 4) (
	input wr_clk, wr_en, rd_clk, rd_en,
	input [DATA_WIDTH-1:0] wr_data,
	input [ADDR_WIDTH:0] wr_ptr, rd_ptr,
	output reg [DATA_WIDTH-1:0] rd_data
);

localparam DEPTH = (1 << ADDR_WIDTH);
reg [DATA_WIDTH-1:0] memory [0:DEPTH-1];

always @ (posedge wr_clk) begin
	if (wr_en)
		memory[wr_ptr[ADDR_WIDTH-1:0]] <= wr_data;
end

always @ (posedge rd_clk) begin
	if (rd_en)
		rd_data <= memory[rd_ptr[ADDR_WIDTH-1:0]];
end

endmodule

gray_to_bin.v
module gray_to_bin #(parameter ADDR_WIDTH = 4) (
	input [ADDR_WIDTH:0] gray,
	output reg [ADDR_WIDTH:0] bin
);

integer i;

always @(*) begin
	bin[ADDR_WIDTH] = gray[ADDR_WIDTH];

	for (i=ADDR_WIDTH-1; i>=0; i=i-1)
		bin[i] = bin[i+1] ^ gray[i];
end

endmodule

dual_flop_synchronizer.v
module dual_flop_synchronizer #(parameter ADDR_WIDTH = 4) (
	input [ADDR_WIDTH:0] data_in,
	input clk, rst,
	output reg [ADDR_WIDTH:0] sync_ff2
);

reg [ADDR_WIDTH:0] sync_ff1;

always @ (posedge clk or negedge rst) begin
	if (!rst) begin
		sync_ff1 <= 0;
		sync_ff2 <= 0;
	end
	else begin
		sync_ff1 <= data_in;
		sync_ff2 <= sync_ff1;
	end
end

endmodule

bin_to_gray.v
module bin_to_gray #(parameter ADDR_WIDTH = 4) (
	input [ADDR_WIDTH:0] bin,
	output reg [ADDR_WIDTH:0] gray
);

integer i;

always@(*) begin
	gray[ADDR_WIDTH] = bin[ADDR_WIDTH];

	for(i=ADDR_WIDTH-1; i>=0; i=i-1)
		gray[i] = bin[i+1] ^ bin[i];
end

endmodule

rd_ptr_handler.v
module rd_ptr_handler #(parameter ADDR_WIDTH = 4) (
	input rd_clk, rd_en, rd_rst,
	input [ADDR_WIDTH:0] wr_ptr_rdclk,
	output reg [ADDR_WIDTH:0] rd_ptr_bin,
	output reg empty
);

wire [ADDR_WIDTH:0] rd_ptr_bin_nxt;
wire empty_nxt;

assign rd_ptr_bin_nxt = rd_ptr_bin + (!empty && rd_en);
assign empty_nxt = (rd_ptr_bin_nxt == wr_ptr_rdclk);

always @ (posedge rd_clk or negedge rd_rst) begin
	if (!rd_rst) begin
		rd_ptr_bin <= 0;
		empty <= 1;
	end
	else begin
		rd_ptr_bin <= rd_ptr_bin_nxt;
		empty <= empty_nxt;
	end
end

endmodule

wr_ptr_handler.v
module wr_ptr_handler #(parameter ADDR_WIDTH = 4)(
	input wr_clk, wr_rst, wr_en,
	input [ADDR_WIDTH:0] rd_ptr_wrclk,
	output reg [ADDR_WIDTH:0] wr_ptr_bin,
	output reg full
);

wire [ADDR_WIDTH:0] wr_ptr_bin_nxt;
wire full_next;

assign wr_ptr_bin_nxt = wr_ptr_bin + (!full && wr_en);
assign full_next = ({~wr_ptr_bin_nxt[ADDR_WIDTH], wr_ptr_bin_nxt[ADDR_WIDTH-1:0]} == rd_ptr_wrclk);

always @ (posedge wr_clk or negedge wr_rst) begin
	if (!wr_rst) begin
		wr_ptr_bin <= 0;
		full <= 0;
	end
	else begin 
		wr_ptr_bin <= wr_ptr_bin_nxt;
		full <= full_next;
	end
end

endmodule

asynchronous_fifo.v
// Modules to be instantiated
`include "fifo_mem.v"
`include "wr_ptr_handler.v"
`include "rd_ptr_handler.v"
`include "dual_flop_synchronizer.v"
`include "bin_to_gray.v"
`include "gray_to_bin.v"

module asynchronous_fifo #(parameter DATA_WIDTH=8, parameter ADDR_WIDTH=4) (
	input wr_clk, rd_clk, wr_rst, rd_rst, wr_en, rd_en,
	input [DATA_WIDTH-1:0] wr_data,
	output [DATA_WIDTH-1:0] rd_data,
	output empty, full
);

// additional wire declarations;
wire [ADDR_WIDTH:0] rd_ptr_wrclk, wr_ptr_bin, wr_ptr_rdclk, rd_ptr_bin, wr_ptr_gray, rd_ptr_gray;
wire [ADDR_WIDTH:0] wr_ptr_gray_rdclk, rd_ptr_gray_wrclk;

// Write Pointer Handler
wr_ptr_handler #(.ADDR_WIDTH(ADDR_WIDTH)) wr_ptr_handler_inst (
	.wr_clk(wr_clk), .wr_rst(wr_rst), .wr_en(wr_en),
	.rd_ptr_wrclk(rd_ptr_wrclk), .wr_ptr_bin(wr_ptr_bin), .full(full)
);

// Read Pointer Handler
rd_ptr_handler #(.ADDR_WIDTH(ADDR_WIDTH)) rd_ptr_handler_inst (
	.rd_clk(rd_clk), .rd_rst(rd_rst), .rd_en(rd_en), 
	.wr_ptr_rdclk(wr_ptr_rdclk), .rd_ptr_bin(rd_ptr_bin),.empty(empty)
);

// Converts binary write pointer to gray write pointer
bin_to_gray #(.ADDR_WIDTH(ADDR_WIDTH)) bin_to_gray_wr (
	.bin(wr_ptr_bin), .gray(wr_ptr_gray)
);

// Converts binary read pointer to gray read pointer
bin_to_gray #(.ADDR_WIDTH(ADDR_WIDTH)) bin_to_gray_rd (
	.bin(rd_ptr_bin), .gray(rd_ptr_gray)
);

// Gray write pointer synchronization with Read clock domain
dual_flop_synchronizer #(.ADDR_WIDTH(ADDR_WIDTH)) sync_wr_to_rd (
	.data_in(wr_ptr_gray), .clk(rd_clk), .rst(rd_rst), .sync_ff2(wr_ptr_gray_rdclk)
);

// Gray read pointer synchronization with Write clock domain
dual_flop_synchronizer #(.ADDR_WIDTH(ADDR_WIDTH)) sync_rd_to_wr (
	.data_in(rd_ptr_gray), .clk(wr_clk), .rst(wr_rst), .sync_ff2(rd_ptr_gray_wrclk)
);

// Converts gray write pointers in read clock domain to binary write pointer
gray_to_bin #(.ADDR_WIDTH(ADDR_WIDTH)) gray_to_bin_wr (
	.gray(wr_ptr_gray_rdclk), .bin(wr_ptr_rdclk)
);

// Converts gray read pointer in write clock domain to binary read pointer
gray_to_bin #(.ADDR_WIDTH(ADDR_WIDTH)) gray_to_bin_rd (
	.gray(rd_ptr_gray_wrclk), .bin(rd_ptr_wrclk)
);

// FIFO Memory
fifo_mem #(.DATA_WIDTH(DATA_WIDTH), .ADDR_WIDTH(ADDR_WIDTH)) fifo_mem_inst (
	.wr_clk(wr_clk), .rd_clk(rd_clk), .wr_en(wr_en && !full), .rd_en(rd_en && !empty), .wr_data(wr_data),
	.rd_data(rd_data), .wr_ptr(wr_ptr_bin), . rd_ptr(rd_ptr_bin)
);

endmodule

asynchronous_fifo_tb.v
`timescale 1ns/1ps

module asynchronous_fifo_tb();

localparam DATA_WIDTH = 8, ADDR_WIDTH = 4;
reg wr_clk, rd_clk, wr_rst, rd_rst, wr_en, rd_en;
reg [DATA_WIDTH-1:0] wr_data;
wire [DATA_WIDTH-1:0] rd_data;
wire empty, full;

asynchronous_fifo #(.DATA_WIDTH(DATA_WIDTH), .ADDR_WIDTH(ADDR_WIDTH)) dut (
	.wr_clk(wr_clk), .rd_clk(rd_clk), .wr_rst(wr_rst), .rd_rst(rd_rst), .wr_en(wr_en),
	.rd_en(rd_en), .wr_data(wr_data),
	.rd_data(rd_data), .empty(empty), .full(full)
);

integer i;

initial begin
	{rd_clk,wr_clk,wr_rst,rd_rst,wr_en,rd_en} = 6'b000000;
	wr_data = 8'h00;
end

always #5 wr_clk = ~wr_clk;
always #10 rd_clk = ~rd_clk;

initial begin
	$dumpfile("wav_asynchronous_fifo.vcd");
	$dumpvars(0,asynchronous_fifo_tb);
	#5 wr_rst = 1'b1; rd_rst = 1'b1; 
	
	/*Writing data into the FIFO (Also checked for 
	overflow condition simultaneously) */
	wr_en = 1'b1;
	#10;
	repeat(18) @(negedge wr_clk) wr_data = wr_data + 1;
	wr_en = 1'b0;

	/* Reading data from the FIFO (Also checked for the
	underflow condition simultaneously)*/
	#20;
	rd_en = 1'b1;
	repeat(18) @ (posedge rd_clk);
	rd_en = 1'b0;

	#50;

	// Simultaenous Read and Write
	wr_en = 1'b1; rd_en = 1'b1;
	repeat(25) @(negedge wr_clk) wr_data = wr_data + 1;	
	wr_en = 1'b0;
	#350 rd_en = 1'b0;
	#20 $finish;
end

endmodule

wav_asynchronous_fifo.vcd
$date
	Tue Jun 23 18:51:51 2026
$end
$version
	Icarus Verilog
$end
$timescale
	1ps
$end
$scope module asynchronous_fifo_tb $end
$var wire 8 ! rd_data [7:0] $end
$var wire 1 " full $end
$var wire 1 # empty $end
$var parameter 32 $ ADDR_WIDTH $end
$var parameter 32 % DATA_WIDTH $end
$var reg 1 & rd_clk $end
$var reg 1 ' rd_en $end
$var reg 1 ( rd_rst $end
$var reg 1 ) wr_clk $end
$var reg 8 * wr_data [7:0] $end
$var reg 1 + wr_en $end
$var reg 1 , wr_rst $end
$scope module dut $end
$var wire 1 & rd_clk $end
$var wire 1 ' rd_en $end
$var wire 1 ( rd_rst $end
$var wire 1 ) wr_clk $end
$var wire 8 - wr_data [7:0] $end
$var wire 1 + wr_en $end
$var wire 1 , wr_rst $end
$var wire 5 . wr_ptr_rdclk [4:0] $end
$var wire 5 / wr_ptr_gray_rdclk [4:0] $end
$var wire 5 0 wr_ptr_gray [4:0] $end
$var wire 5 1 wr_ptr_bin [4:0] $end
$var wire 5 2 rd_ptr_wrclk [4:0] $end
$var wire 5 3 rd_ptr_gray_wrclk [4:0] $end
$var wire 5 4 rd_ptr_gray [4:0] $end
$var wire 5 5 rd_ptr_bin [4:0] $end
$var wire 8 6 rd_data [7:0] $end
$var wire 1 " full $end
$var wire 1 # empty $end
$var parameter 32 7 ADDR_WIDTH $end
$var parameter 32 8 DATA_WIDTH $end
$scope module bin_to_gray_rd $end
$var wire 5 9 bin [4:0] $end
$var parameter 32 : ADDR_WIDTH $end
$var reg 5 ; gray [4:0] $end
$var integer 32 < i [31:0] $end
$upscope $end
$scope module bin_to_gray_wr $end
$var wire 5 = bin [4:0] $end
$var parameter 32 > ADDR_WIDTH $end
$var reg 5 ? gray [4:0] $end
$var integer 32 @ i [31:0] $end
$upscope $end
$scope module fifo_mem_inst $end
$var wire 1 & rd_clk $end
$var wire 1 A rd_en $end
$var wire 1 ) wr_clk $end
$var wire 8 B wr_data [7:0] $end
$var wire 1 C wr_en $end
$var wire 5 D wr_ptr [4:0] $end
$var wire 5 E rd_ptr [4:0] $end
$var parameter 32 F ADDR_WIDTH $end
$var parameter 32 G DATA_WIDTH $end
$var parameter 36 H DEPTH $end
$var reg 8 I rd_data [7:0] $end
$upscope $end
$scope module gray_to_bin_rd $end
$var wire 5 J gray [4:0] $end
$var parameter 32 K ADDR_WIDTH $end
$var reg 5 L bin [4:0] $end
$var integer 32 M i [31:0] $end
$upscope $end
$scope module gray_to_bin_wr $end
$var wire 5 N gray [4:0] $end
$var parameter 32 O ADDR_WIDTH $end
$var reg 5 P bin [4:0] $end
$var integer 32 Q i [31:0] $end
$upscope $end
$scope module rd_ptr_handler_inst $end
$var wire 1 & rd_clk $end
$var wire 1 ' rd_en $end
$var wire 1 ( rd_rst $end
$var wire 5 R wr_ptr_rdclk [4:0] $end
$var wire 5 S rd_ptr_bin_nxt [4:0] $end
$var wire 1 T empty_nxt $end
$var parameter 32 U ADDR_WIDTH $end
$var reg 1 # empty $end
$var reg 5 V rd_ptr_bin [4:0] $end
$upscope $end
$scope module sync_rd_to_wr $end
$var wire 1 ) clk $end
$var wire 5 W data_in [4:0] $end
$var wire 1 , rst $end
$var parameter 32 X ADDR_WIDTH $end
$var reg 5 Y sync_ff1 [4:0] $end
$var reg 5 Z sync_ff2 [4:0] $end
$upscope $end
$scope module sync_wr_to_rd $end
$var wire 1 & clk $end
$var wire 5 [ data_in [4:0] $end
$var wire 1 ( rst $end
$var parameter 32 \ ADDR_WIDTH $end
$var reg 5 ] sync_ff1 [4:0] $end
$var reg 5 ^ sync_ff2 [4:0] $end
$upscope $end
$scope module wr_ptr_handler_inst $end
$var wire 5 _ rd_ptr_wrclk [4:0] $end
$var wire 1 ) wr_clk $end
$var wire 1 + wr_en $end
$var wire 1 , wr_rst $end
$var wire 5 ` wr_ptr_bin_nxt [4:0] $end
$var wire 1 a full_next $end
$var parameter 32 b ADDR_WIDTH $end
$var reg 1 " full $end
$var reg 5 c wr_ptr_bin [4:0] $end
$upscope $end
$upscope $end
$upscope $end
$enddefinitions $end
$comment Show the parameter values. $end
$dumpall
b100 b
b100 \
b100 X
b100 U
b100 O
b100 K
b10000 H
b1000 G
b100 F
b100 >
b100 :
b1000 8
b100 7
b1000 %
b100 $
$end
#0
$dumpvars
b0 c
0a
b0 `
b0 _
b0 ^
b0 ]
b0 [
b0 Z
b0 Y
b0 W
b0 V
1T
b0 S
b0 R
b11111111111111111111111111111111 Q
b0 P
b0 N
b11111111111111111111111111111111 M
b0 L
b0 J
bx I
b0 E
b0 D
0C
b0 B
0A
b11111111111111111111111111111111 @
b0 ?
b0 =
b11111111111111111111111111111111 <
b0 ;
b0 9
bx 6
b0 5
b0 4
b0 3
b0 2
b0 1
b0 0
b0 /
b0 .
b0 -
0,
0+
b0 *
0)
0(
0'
0&
1#
0"
bx !
$end
#5000
1C
b1 `
1+
1(
1,
1)
#10000
0)
1&
#15000
b1 0
b1 ?
b1 [
b11111111111111111111111111111111 @
b10 `
b1 1
b1 =
b1 D
b1 c
1)
#20000
b1 *
b1 -
b1 B
0)
0&
#25000
b11 0
b11 ?
b11 [
b11111111111111111111111111111111 @
b11 `
b10 1
b10 =
b10 D
b10 c
1)
#30000
b11 ]
b10 *
b10 -
b10 B
0)
1&
#35000
b10 0
b10 ?
b10 [
b11111111111111111111111111111111 @
b100 `
b11 1
b11 =
b11 D
b11 c
1)
#40000
b11 *
b11 -
b11 B
0)
0&
#45000
b110 0
b110 ?
b110 [
b11111111111111111111111111111111 @
b101 `
b100 1
b100 =
b100 D
b100 c
1)
#50000
0T
b10 .
b10 P
b10 R
b11111111111111111111111111111111 Q
b11 /
b11 N
b11 ^
b110 ]
b100 *
b100 -
b100 B
0)
1&
#55000
b111 0
b111 ?
b111 [
b11111111111111111111111111111111 @
b110 `
b101 1
b101 =
b101 D
b101 c
1)
#60000
b101 *
b101 -
b101 B
0)
0&
#65000
b101 0
b101 ?
b101 [
b11111111111111111111111111111111 @
b111 `
b110 1
b110 =
b110 D
b110 c
1)
#70000
b100 .
b100 P
b100 R
b11111111111111111111111111111111 Q
0#
b110 /
b110 N
b110 ^
b101 ]
b110 *
b110 -
b110 B
0)
1&
#75000
b100 0
b100 ?
b100 [
b11111111111111111111111111111111 @
b1000 `
b111 1
b111 =
b111 D
b111 c
1)
#80000
b111 *
b111 -
b111 B
0)
0&
#85000
b1100 0
b1100 ?
b1100 [
b11111111111111111111111111111111 @
b1001 `
b1000 1
b1000 =
b1000 D
b1000 c
1)
#90000
b110 .
b110 P
b110 R
b11111111111111111111111111111111 Q
b101 /
b101 N
b101 ^
b1100 ]
b1000 *
b1000 -
b1000 B
0)
1&
#95000
b1101 0
b1101 ?
b1101 [
b11111111111111111111111111111111 @
b1010 `
b1001 1
b1001 =
b1001 D
b1001 c
1)
#100000
b1001 *
b1001 -
b1001 B
0)
0&
#105000
b1111 0
b1111 ?
b1111 [
b11111111111111111111111111111111 @
b1011 `
b1010 1
b1010 =
b1010 D
b1010 c
1)
#110000
b1000 .
b1000 P
b1000 R
b11111111111111111111111111111111 Q
b1100 /
b1100 N
b1100 ^
b1111 ]
b1010 *
b1010 -
b1010 B
0)
1&
#115000
b1110 0
b1110 ?
b1110 [
b11111111111111111111111111111111 @
b1100 `
b1011 1
b1011 =
b1011 D
b1011 c
1)
#120000
b1011 *
b1011 -
b1011 B
0)
0&
#125000
b1010 0
b1010 ?
b1010 [
b11111111111111111111111111111111 @
b1101 `
b1100 1
b1100 =
b1100 D
b1100 c
1)
#130000
b1010 .
b1010 P
b1010 R
b11111111111111111111111111111111 Q
b1111 /
b1111 N
b1111 ^
b1010 ]
b1100 *
b1100 -
b1100 B
0)
1&
#135000
b1011 0
b1011 ?
b1011 [
b11111111111111111111111111111111 @
b1110 `
b1101 1
b1101 =
b1101 D
b1101 c
1)
#140000
b1101 *
b1101 -
b1101 B
0)
0&
#145000
b1001 0
b1001 ?
b1001 [
b11111111111111111111111111111111 @
b1111 `
b1110 1
b1110 =
b1110 D
b1110 c
1)
#150000
b1100 .
b1100 P
b1100 R
b11111111111111111111111111111111 Q
b1010 /
b1010 N
b1010 ^
b1001 ]
b1110 *
b1110 -
b1110 B
0)
1&
#155000
1a
b1000 0
b1000 ?
b1000 [
b11111111111111111111111111111111 @
b10000 `
b1111 1
b1111 =
b1111 D
b1111 c
1)
#160000
b1111 *
b1111 -
b1111 B
0)
0&
#165000
0C
1a
b11111111111111111111111111111111 @
b11000 0
b11000 ?
b11000 [
1"
b10000 `
b10000 1
b10000 =
b10000 D
b10000 c
1)
#170000
b1110 .
b1110 P
b1110 R
b11111111111111111111111111111111 Q
b1001 /
b1001 N
b1001 ^
b11000 ]
b10000 *
b10000 -
b10000 B
0)
1&
#175000
1)
#180000
b10001 *
b10001 -
b10001 B
0)
0&
#185000
1)
#190000
b11111111111111111111111111111111 Q
b10000 .
b10000 P
b10000 R
b11000 /
b11000 N
b11000 ^
0+
b10010 *
b10010 -
b10010 B
0)
1&
#195000
1)
#200000
0)
0&
#205000
1)
#210000
b1 4
b1 ;
b1 W
b11111111111111111111111111111111 <
b0 !
b0 6
b0 I
b1 5
b1 9
b1 E
b1 V
1A
b10 S
0)
1&
1'
#215000
b1 Y
1)
#220000
0)
0&
#225000
0a
b1 2
b1 L
b1 _
b11111111111111111111111111111111 M
b1 3
b1 J
b1 Z
1)
#230000
b11 4
b11 ;
b11 W
b11111111111111111111111111111111 <
b1 !
b1 6
b1 I
b11 S
b10 5
b10 9
b10 E
b10 V
0)
1&
#235000
0"
b11 Y
1)
#240000
0)
0&
#245000
b10 2
b10 L
b10 _
b11111111111111111111111111111111 M
b11 3
b11 J
b11 Z
1)
#250000
b10 4
b10 ;
b10 W
b11111111111111111111111111111111 <
b10 !
b10 6
b10 I
b100 S
b11 5
b11 9
b11 E
b11 V
0)
1&
#255000
b10 Y
1)
#260000
0)
0&
#265000
b11 2
b11 L
b11 _
b11111111111111111111111111111111 M
b10 3
b10 J
b10 Z
1)
#270000
b110 4
b110 ;
b110 W
b11111111111111111111111111111111 <
b11 !
b11 6
b11 I
b101 S
b100 5
b100 9
b100 E
b100 V
0)
1&
#275000
b110 Y
1)
#280000
0)
0&
#285000
b100 2
b100 L
b100 _
b11111111111111111111111111111111 M
b110 3
b110 J
b110 Z
1)
#290000
b111 4
b111 ;
b111 W
b11111111111111111111111111111111 <
b100 !
b100 6
b100 I
b110 S
b101 5
b101 9
b101 E
b101 V
0)
1&
#295000
b111 Y
1)
#300000
0)
0&
#305000
b101 2
b101 L
b101 _
b11111111111111111111111111111111 M
b111 3
b111 J
b111 Z
1)
#310000
b101 4
b101 ;
b101 W
b11111111111111111111111111111111 <
b101 !
b101 6
b101 I
b111 S
b110 5
b110 9
b110 E
b110 V
0)
1&
#315000
b101 Y
1)
#320000
0)
0&
#325000
b110 2
b110 L
b110 _
b11111111111111111111111111111111 M
b101 3
b101 J
b101 Z
1)
#330000
b100 4
b100 ;
b100 W
b11111111111111111111111111111111 <
b110 !
b110 6
b110 I
b1000 S
b111 5
b111 9
b111 E
b111 V
0)
1&
#335000
b100 Y
1)
#340000
0)
0&
#345000
b111 2
b111 L
b111 _
b11111111111111111111111111111111 M
b100 3
b100 J
b100 Z
1)
#350000
b1100 4
b1100 ;
b1100 W
b11111111111111111111111111111111 <
b111 !
b111 6
b111 I
b1001 S
b1000 5
b1000 9
b1000 E
b1000 V
0)
1&
#355000
b1100 Y
1)
#360000
0)
0&
#365000
b1000 2
b1000 L
b1000 _
b11111111111111111111111111111111 M
b1100 3
b1100 J
b1100 Z
1)
#370000
b1101 4
b1101 ;
b1101 W
b11111111111111111111111111111111 <
b1000 !
b1000 6
b1000 I
b1010 S
b1001 5
b1001 9
b1001 E
b1001 V
0)
1&
#375000
b1101 Y
1)
#380000
0)
0&
#385000
b1001 2
b1001 L
b1001 _
b11111111111111111111111111111111 M
b1101 3
b1101 J
b1101 Z
1)
#390000
b1111 4
b1111 ;
b1111 W
b11111111111111111111111111111111 <
b1001 !
b1001 6
b1001 I
b1011 S
b1010 5
b1010 9
b1010 E
b1010 V
0)
1&
#395000
b1111 Y
1)
#400000
0)
0&
#405000
b1010 2
b1010 L
b1010 _
b11111111111111111111111111111111 M
b1111 3
b1111 J
b1111 Z
1)
#410000
b1110 4
b1110 ;
b1110 W
b11111111111111111111111111111111 <
b1010 !
b1010 6
b1010 I
b1100 S
b1011 5
b1011 9
b1011 E
b1011 V
0)
1&
#415000
b1110 Y
1)
#420000
0)
0&
#425000
b1011 2
b1011 L
b1011 _
b11111111111111111111111111111111 M
b1110 3
b1110 J
b1110 Z
1)
#430000
b1010 4
b1010 ;
b1010 W
b11111111111111111111111111111111 <
b1011 !
b1011 6
b1011 I
b1101 S
b1100 5
b1100 9
b1100 E
b1100 V
0)
1&
#435000
b1010 Y
1)
#440000
0)
0&
#445000
b1100 2
b1100 L
b1100 _
b11111111111111111111111111111111 M
b1010 3
b1010 J
b1010 Z
1)
#450000
b1011 4
b1011 ;
b1011 W
b11111111111111111111111111111111 <
b1100 !
b1100 6
b1100 I
b1110 S
b1101 5
b1101 9
b1101 E
b1101 V
0)
1&
#455000
b1011 Y
1)
#460000
0)
0&
#465000
b1101 2
b1101 L
b1101 _
b11111111111111111111111111111111 M
b1011 3
b1011 J
b1011 Z
1)
#470000
b1001 4
b1001 ;
b1001 W
b11111111111111111111111111111111 <
b1101 !
b1101 6
b1101 I
b1111 S
b1110 5
b1110 9
b1110 E
b1110 V
0)
1&
#475000
b1001 Y
1)
#480000
0)
0&
#485000
b1110 2
b1110 L
b1110 _
b11111111111111111111111111111111 M
b1001 3
b1001 J
b1001 Z
1)
#490000
b1000 4
b1000 ;
b1000 W
b11111111111111111111111111111111 <
b1110 !
b1110 6
b1110 I
1T
b10000 S
b1111 5
b1111 9
b1111 E
b1111 V
0)
1&
#495000
b1000 Y
1)
#500000
0)
0&
#505000
b1111 2
b1111 L
b1111 _
b11111111111111111111111111111111 M
b1000 3
b1000 J
b1000 Z
1)
#510000
0A
b11111111111111111111111111111111 <
b11000 4
b11000 ;
b11000 W
b1111 !
b1111 6
b1111 I
1#
1T
b10000 S
b10000 5
b10000 9
b10000 E
b10000 V
0)
1&
#515000
b11000 Y
1)
#520000
0)
0&
#525000
b11111111111111111111111111111111 M
b10000 2
b10000 L
b10000 _
b11000 3
b11000 J
b11000 Z
1)
#530000
0)
1&
#535000
1)
#540000
0)
0&
#545000
1)
#550000
0'
0)
1&
#555000
1)
#560000
0)
0&
#565000
1)
#570000
0)
1&
#575000
1)
#580000
0)
0&
#585000
1)
#590000
0)
1&
#595000
1)
#600000
b10011 *
b10011 -
b10011 B
1C
b10001 `
0)
0&
1'
1+
#605000
b11001 0
b11001 ?
b11001 [
b11111111111111111111111111111111 @
b10010 `
b10001 1
b10001 =
b10001 D
b10001 c
1)
#610000
b11001 ]
b10100 *
b10100 -
b10100 B
0)
1&
#615000
b11011 0
b11011 ?
b11011 [
b11111111111111111111111111111111 @
b10011 `
b10010 1
b10010 =
b10010 D
b10010 c
1)
#620000
b10101 *
b10101 -
b10101 B
0)
0&
#625000
b11010 0
b11010 ?
b11010 [
b11111111111111111111111111111111 @
b10100 `
b10011 1
b10011 =
b10011 D
b10011 c
1)
#630000
0T
b10001 .
b10001 P
b10001 R
b11111111111111111111111111111111 Q
b11001 /
b11001 N
b11001 ^
b11010 ]
b10110 *
b10110 -
b10110 B
0)
1&
#635000
b11110 0
b11110 ?
b11110 [
b11111111111111111111111111111111 @
b10101 `
b10100 1
b10100 =
b10100 D
b10100 c
1)
#640000
b10111 *
b10111 -
b10111 B
0)
0&
#645000
b11111 0
b11111 ?
b11111 [
b11111111111111111111111111111111 @
b10110 `
b10101 1
b10101 =
b10101 D
b10101 c
1)
#650000
b10011 .
b10011 P
b10011 R
b11111111111111111111111111111111 Q
0T
b10001 S
1A
b11010 /
b11010 N
b11010 ^
b11111 ]
0#
b11000 *
b11000 -
b11000 B
0)
1&
#655000
b11101 0
b11101 ?
b11101 [
b11111111111111111111111111111111 @
b10111 `
b10110 1
b10110 =
b10110 D
b10110 c
1)
#660000
b11001 *
b11001 -
b11001 B
0)
0&
#665000
b11100 0
b11100 ?
b11100 [
b11111111111111111111111111111111 @
b11000 `
b10111 1
b10111 =
b10111 D
b10111 c
1)
#670000
b11001 4
b11001 ;
b11001 W
b11111111111111111111111111111111 <
b10101 .
b10101 P
b10101 R
b11111111111111111111111111111111 Q
b10011 !
b10011 6
b10011 I
b10010 S
b10001 5
b10001 9
b10001 E
b10001 V
b11111 /
b11111 N
b11111 ^
b11100 ]
b11010 *
b11010 -
b11010 B
0)
1&
#675000
b10100 0
b10100 ?
b10100 [
b11111111111111111111111111111111 @
b11001 `
b11000 1
b11000 =
b11000 D
b11000 c
b11001 Y
1)
#680000
b11011 *
b11011 -
b11011 B
0)
0&
#685000
b10001 2
b10001 L
b10001 _
b11111111111111111111111111111111 M
b10101 0
b10101 ?
b10101 [
b11111111111111111111111111111111 @
b11001 3
b11001 J
b11001 Z
b11010 `
b11001 1
b11001 =
b11001 D
b11001 c
1)
#690000
b10111 .
b10111 P
b10111 R
b11111111111111111111111111111111 Q
b11011 4
b11011 ;
b11011 W
b11111111111111111111111111111111 <
b10100 !
b10100 6
b10100 I
b11100 /
b11100 N
b11100 ^
b10101 ]
b10011 S
b10010 5
b10010 9
b10010 E
b10010 V
b11100 *
b11100 -
b11100 B
0)
1&
#695000
b10111 0
b10111 ?
b10111 [
b11111111111111111111111111111111 @
b11011 `
b11010 1
b11010 =
b11010 D
b11010 c
b11011 Y
1)
#700000
b11101 *
b11101 -
b11101 B
0)
0&
#705000
b10010 2
b10010 L
b10010 _
b11111111111111111111111111111111 M
b10110 0
b10110 ?
b10110 [
b11111111111111111111111111111111 @
b11011 3
b11011 J
b11011 Z
b11100 `
b11011 1
b11011 =
b11011 D
b11011 c
1)
#710000
b11010 4
b11010 ;
b11010 W
b11111111111111111111111111111111 <
b11001 .
b11001 P
b11001 R
b11111111111111111111111111111111 Q
b10101 !
b10101 6
b10101 I
b10100 S
b10011 5
b10011 9
b10011 E
b10011 V
b10101 /
b10101 N
b10101 ^
b10110 ]
b11110 *
b11110 -
b11110 B
0)
1&
#715000
b10010 0
b10010 ?
b10010 [
b11111111111111111111111111111111 @
b11101 `
b11100 1
b11100 =
b11100 D
b11100 c
b11010 Y
1)
#720000
b11111 *
b11111 -
b11111 B
0)
0&
#725000
b10011 2
b10011 L
b10011 _
b11111111111111111111111111111111 M
b10011 0
b10011 ?
b10011 [
b11111111111111111111111111111111 @
b11010 3
b11010 J
b11010 Z
b11110 `
b11101 1
b11101 =
b11101 D
b11101 c
1)
#730000
b11011 .
b11011 P
b11011 R
b11111111111111111111111111111111 Q
b11110 4
b11110 ;
b11110 W
b11111111111111111111111111111111 <
b10110 !
b10110 6
b10110 I
b10110 /
b10110 N
b10110 ^
b10011 ]
b10101 S
b10100 5
b10100 9
b10100 E
b10100 V
b100000 *
b100000 -
b100000 B
0)
1&
#735000
b10001 0
b10001 ?
b10001 [
b11111111111111111111111111111111 @
b11111 `
b11110 1
b11110 =
b11110 D
b11110 c
b11110 Y
1)
#740000
b100001 *
b100001 -
b100001 B
0)
0&
#745000
b10100 2
b10100 L
b10100 _
b11111111111111111111111111111111 M
b10000 0
b10000 ?
b10000 [
b11111111111111111111111111111111 @
b11110 3
b11110 J
b11110 Z
b0 `
b11111 1
b11111 =
b11111 D
b11111 c
1)
#750000
b11111 4
b11111 ;
b11111 W
b11111111111111111111111111111111 <
b11101 .
b11101 P
b11101 R
b11111111111111111111111111111111 Q
b10111 !
b10111 6
b10111 I
b10110 S
b10101 5
b10101 9
b10101 E
b10101 V
b10011 /
b10011 N
b10011 ^
b10000 ]
b100010 *
b100010 -
b100010 B
0)
1&
#755000
b11111111111111111111111111111111 @
b0 0
b0 ?
b0 [
b1 `
b0 1
b0 =
b0 D
b0 c
b11111 Y
1)
#760000
b100011 *
b100011 -
b100011 B
0)
0&
#765000
b10101 2
b10101 L
b10101 _
b11111111111111111111111111111111 M
b1 0
b1 ?
b1 [
b11111111111111111111111111111111 @
b11111 3
b11111 J
b11111 Z
b10 `
b1 1
b1 =
b1 D
b1 c
1)
#770000
b11111 .
b11111 P
b11111 R
b11111111111111111111111111111111 Q
b11101 4
b11101 ;
b11101 W
b11111111111111111111111111111111 <
b11000 !
b11000 6
b11000 I
b10000 /
b10000 N
b10000 ^
b1 ]
b10111 S
b10110 5
b10110 9
b10110 E
b10110 V
b100100 *
b100100 -
b100100 B
0)
1&
#775000
b11 0
b11 ?
b11 [
b11111111111111111111111111111111 @
b11 `
b10 1
b10 =
b10 D
b10 c
b11101 Y
1)
#780000
b100101 *
b100101 -
b100101 B
0)
0&
#785000
b10110 2
b10110 L
b10110 _
b11111111111111111111111111111111 M
b10 0
b10 ?
b10 [
b11111111111111111111111111111111 @
b11101 3
b11101 J
b11101 Z
b100 `
b11 1
b11 =
b11 D
b11 c
1)
#790000
b11100 4
b11100 ;
b11100 W
b11111111111111111111111111111111 <
b11111111111111111111111111111111 Q
b1 .
b1 P
b1 R
b11001 !
b11001 6
b11001 I
b11000 S
b10111 5
b10111 9
b10111 E
b10111 V
b1 /
b1 N
b1 ^
b10 ]
b100110 *
b100110 -
b100110 B
0)
1&
#795000
b110 0
b110 ?
b110 [
b11111111111111111111111111111111 @
b101 `
b100 1
b100 =
b100 D
b100 c
b11100 Y
1)
